llama_iris/__init__.py
llama_iris/vectorstore.py
llama_iris-0.5.0.dist-info/LICENSE
llama_iris-0.5.0.dist-info/METADATA
llama_iris-0.5.0.dist-info/WHEEL
llama_iris-0.5.0.dist-info/RECORD
