Metadata-Version: 2.1
Name: llama-iris
Version: 0.5.0
Summary: Interface between LLMs and your data
Home-page: https://github.com/caretdev/llama-iris
License: MIT
Keywords: LLM,NLP,RAG,data,devtools,index,retrieval,iris
Author: Dmitry Maslennikov
Author-email: dmitry@caretdev.com
Requires-Python: >=3.9,<4.0
Classifier: License :: OSI Approved :: MIT License
Classifier: Programming Language :: Python :: 3
Classifier: Programming Language :: Python :: 3.9
Classifier: Programming Language :: Python :: 3.10
Classifier: Programming Language :: Python :: 3.11
Classifier: Programming Language :: Python :: 3.12
Classifier: Topic :: Scientific/Engineering :: Artificial Intelligence
Classifier: Topic :: Software Development :: Libraries :: Application Frameworks
Classifier: Topic :: Software Development :: Libraries :: Python Modules
Requires-Dist: SQLAlchemy[asyncio] (>=1.4.49)
Requires-Dist: llama-index (>=0.10.0,<0.11.0)
Requires-Dist: pandas (>=2.2.0,<3.0.0)
Requires-Dist: sqlalchemy-iris (>=0.14.0,<0.15.0)
Project-URL: Repository, https://github.com/caretdev/llama-iris
